handict/__init__.py
handict/handict.py
handict/trie.py
handict-0.2.0.dist-info/METADATA
handict-0.2.0.dist-info/WHEEL
handict-0.2.0.dist-info/entry_points.txt
handict-0.2.0.dist-info/top_level.txt
handict-0.2.0.dist-info/RECORD
