Metadata-Version: 2.1
Name: handict
Version: 0.2.0
Summary: Yet another word segmentation tool.
Home-page: https://github.com/kemingy/handict
Author: Keming Yang
Author-email: kemingy94@gmail.com
License: UNKNOWN
Platform: UNKNOWN
Classifier: Programming Language :: Python :: 3 :: Only
Classifier: Programming Language :: Python :: 3.6
Classifier: Programming Language :: Python :: 3.7
Classifier: Programming Language :: Python :: 3.8
Classifier: Operating System :: OS Independent
Classifier: Topic :: Software Development :: Libraries :: Python Modules
Requires-Python: >=3.6
